<?xml version="1.0"?>
<?xml-stylesheet type="text/xsl" href="style.xsl"?>
<STAT>
<TAG>ALL</TAG>
<VAR>Visibility</VAR>
<UNIT>m</UNIT>
<PERIOD>20211110-20211201</PERIOD>
 <STATION>
 <MEAN_OBS>   14381.4434     </MEAN_OBS>
 <STDV_OBS>   15942.4307     </STDV_OBS>
 <EXP>
 <ID>        1115 </ID>
 <NAME>REF</NAME>
 <NUM>         291 </NUM>
 <MEAN>   37645.6055     </MEAN>
 <STDV>   3.35177996E-11 </STDV>
 <BIAS>   13518.7246     </BIAS>
 <RMSE>  0.655538559     </RMSE>
 <CORR>  -3.74685934E-20 </CORR>
 </EXP>
 <EXP>
 <ID>        1115 </ID>
 <NAME>SAR_2</NAME>
 <NUM>         291 </NUM>
 <MEAN>   1.40129846E-45 </MEAN>
 <STDV>   1.40129846E-45 </STDV>
 <BIAS>   13717.0469     </BIAS>
 <RMSE>  0.656028807     </RMSE>
 <CORR>   0.00000000     </CORR>
 </EXP>
 </STATION>
 <STATION>
 <MEAN_OBS>   17139.3926     </MEAN_OBS>
 <STDV_OBS>   16165.0947     </STDV_OBS>
 <EXP>
 <ID>       20046 </ID>
 <NAME>REF</NAME>
 <NUM>         330 </NUM>
 <MEAN>   33970.9102     </MEAN>
 <STDV>   3.35181327E-11 </STDV>
 <BIAS>   15328.7705     </BIAS>
 <RMSE>  0.301649123     </RMSE>
 <CORR>   3.35176886E-11 </CORR>
 </EXP>
 <EXP>
 <ID>       20046 </ID>
 <NAME>SAR_2</NAME>
 <NUM>         330 </NUM>
 <MEAN>   0.00000000     </MEAN>
 <STDV>   1.40129846E-45 </STDV>
 <BIAS>   15267.2295     </BIAS>
 <RMSE>  0.328515530     </RMSE>
 <CORR>   1.40129846E-45 </CORR>
 </EXP>
 </STATION>
 <STATION>
 <MEAN_OBS>   40341.8945     </MEAN_OBS>
 <STDV_OBS>   19839.5234     </STDV_OBS>
 <EXP>
 <ID>        1065 </ID>
 <NAME>REF</NAME>
 <NUM>         148 </NUM>
 <MEAN>   24291.4434     </MEAN>
 <STDV>   3.34755001E-11 </STDV>
 <BIAS>   31070.1680     </BIAS>
 <RMSE>  0.306979358     </RMSE>
 <CORR>   3.35176886E-11 </CORR>
 </EXP>
 <EXP>
 <ID>        1065 </ID>
 <NAME>SAR_2</NAME>
 <NUM>         148 </NUM>
 <MEAN>   1.40129846E-45 </MEAN>
 <STDV>   1.40129846E-45 </STDV>
 <BIAS>   33690.4766     </BIAS>
 <RMSE>  0.168008685     </RMSE>
 <CORR>   1.40129846E-45 </CORR>
 </EXP>
 </STATION>
 <STATION>
 <MEAN_OBS>   34666.9102     </MEAN_OBS>
 <STDV_OBS>   20574.8203     </STDV_OBS>
 <EXP>
 <ID>        1199 </ID>
 <NAME>REF</NAME>
 <NUM>         136 </NUM>
 <MEAN>   21796.8379     </MEAN>
 <STDV>  -3.74675594E-20 </STDV>
 <BIAS>   21467.9512     </BIAS>
 <RMSE>  0.255217016     </RMSE>
 <CORR>  -3.74685934E-20 </CORR>
 </EXP>
 <EXP>
 <ID>        1199 </ID>
 <NAME>SAR_2</NAME>
 <NUM>         136 </NUM>
 <MEAN>   1.40129846E-45 </MEAN>
 <STDV>   0.00000000     </STDV>
 <BIAS>   21559.2305     </BIAS>
 <RMSE>  0.207258329     </RMSE>
 <CORR>   0.00000000     </CORR>
 </EXP>
 </STATION>
 <STATION>
 <MEAN_OBS>   28652.4062     </MEAN_OBS>
 <STDV_OBS>   16208.5869     </STDV_OBS>
 <EXP>
 <ID>        1108 </ID>
 <NAME>REF</NAME>
 <NUM>         187 </NUM>
 <MEAN>   30792.4238     </MEAN>
 <STDV>   3.35177996E-11 </STDV>
 <BIAS>   27987.5176     </BIAS>
 <RMSE>  0.430101037     </RMSE>
 <CORR>   3.35176886E-11 </CORR>
 </EXP>
 <EXP>
 <ID>        1108 </ID>
 <NAME>SAR_2</NAME>
 <NUM>         187 </NUM>
 <MEAN>   1.40129846E-45 </MEAN>
 <STDV>   1.40129846E-45 </STDV>
 <BIAS>   28475.5410     </BIAS>
 <RMSE>  0.401792675     </RMSE>
 <CORR>   1.40129846E-45 </CORR>
 </EXP>
 </STATION>
 <STATION>
 <MEAN_OBS>   6563.87109     </MEAN_OBS>
 <STDV_OBS>   18508.5039     </STDV_OBS>
 <EXP>
 <ID>        1150 </ID>
 <NAME>REF</NAME>
 <NUM>         155 </NUM>
 <MEAN>   16356.8896     </MEAN>
 <STDV>   3.35181327E-11 </STDV>
 <BIAS>   16462.3242     </BIAS>
 <RMSE>  0.622076154     </RMSE>
 <CORR>   3.35180217E-11 </CORR>
 </EXP>
 <EXP>
 <ID>        1150 </ID>
 <NAME>SAR_2</NAME>
 <NUM>         155 </NUM>
 <MEAN>   0.00000000     </MEAN>
 <STDV>   1.40129846E-45 </STDV>
 <BIAS>   16974.8848     </BIAS>
 <RMSE>  0.659901381     </RMSE>
 <CORR>   1.40129846E-45 </CORR>
 </EXP>
 </STATION>
 <STATION>
 <MEAN_OBS>   47540.8164     </MEAN_OBS>
 <STDV_OBS>   14630.1826     </STDV_OBS>
 <EXP>
 <ID>        1152 </ID>
 <NAME>REF</NAME>
 <NUM>         294 </NUM>
 <MEAN>   31495.0918     </MEAN>
 <STDV>  -3.74684900E-20 </STDV>
 <BIAS>   20346.5996     </BIAS>
 <RMSE>  0.272295415     </RMSE>
 <CORR>   3.35176886E-11 </CORR>
 </EXP>
 <EXP>
 <ID>        1152 </ID>
 <NAME>SAR_2</NAME>
 <NUM>         294 </NUM>
 <MEAN>   0.00000000     </MEAN>
 <STDV>   0.00000000     </STDV>
 <BIAS>   20476.9766     </BIAS>
 <RMSE>  0.276672065     </RMSE>
 <CORR>   1.40129846E-45 </CORR>
 </EXP>
 </STATION>
 <STATION>
 <MEAN_OBS>   9338.78711     </MEAN_OBS>
 <STDV_OBS>   8538.72852     </STDV_OBS>
 <EXP>
 <ID>       20107 </ID>
 <NAME>REF</NAME>
 <NUM>         330 </NUM>
 <MEAN>   46314.0156     </MEAN>
 <STDV>   0.00000000     </STDV>
 <BIAS>   10965.8145     </BIAS>
 <RMSE>  0.115979455     </RMSE>
 <CORR>   3.34758332E-11 </CORR>
 </EXP>
 <EXP>
 <ID>       20107 </ID>
 <NAME>SAR_2</NAME>
 <NUM>         330 </NUM>
 <MEAN>   7.46051302E-42 </MEAN>
 <STDV>   0.00000000     </STDV>
 <BIAS>   9095.77832     </BIAS>
 <RMSE>  0.140598103     </RMSE>
 <CORR>   1.40129846E-45 </CORR>
 </EXP>
 </STATION>
 <STATION>
 <MEAN_OBS>   35419.3945     </MEAN_OBS>
 <STDV_OBS>   16811.3691     </STDV_OBS>
 <EXP>
 <ID>       22003 </ID>
 <NAME>REF</NAME>
 <NUM>         330 </NUM>
 <MEAN>   36410.5977     </MEAN>
 <STDV>  -3.74677662E-20 </STDV>
 <BIAS>   21239.6973     </BIAS>
 <RMSE>  0.346972913     </RMSE>
 <CORR>  -3.74675594E-20 </CORR>
 </EXP>
 <EXP>
 <ID>       22003 </ID>
 <NAME>SAR_2</NAME>
 <NUM>         330 </NUM>
 <MEAN>   1.40129846E-45 </MEAN>
 <STDV>   0.00000000     </STDV>
 <BIAS>   21116.8242     </BIAS>
 <RMSE>  0.327268332     </RMSE>
 <CORR>   0.00000000     </CORR>
 </EXP>
 </STATION>
 <STATION>
 <MEAN_OBS>   41336.3633     </MEAN_OBS>
 <STDV_OBS>   18828.6309     </STDV_OBS>
 <EXP>
 <ID>       22004 </ID>
 <NAME>REF</NAME>
 <NUM>         330 </NUM>
 <MEAN>   24914.6367     </MEAN>
 <STDV>   3.34758332E-11 </STDV>
 <BIAS>   21380.2637     </BIAS>
 <RMSE>  0.287597507     </RMSE>
 <CORR>   3.35176886E-11 </CORR>
 </EXP>
 <EXP>
 <ID>       22004 </ID>
 <NAME>SAR_2</NAME>
 <NUM>         330 </NUM>
 <MEAN>   0.00000000     </MEAN>
 <STDV>   1.40129846E-45 </STDV>
 <BIAS>   21014.7656     </BIAS>
 <RMSE>  0.300683975     </RMSE>
 <CORR>   1.40129846E-45 </CORR>
 </EXP>
 </STATION>
 <STATION>
 <MEAN_OBS>   12921.2119     </MEAN_OBS>
 <STDV_OBS>   17915.9121     </STDV_OBS>
 <EXP>
 <ID>       22113 </ID>
 <NAME>REF</NAME>
 <NUM>         330 </NUM>
 <MEAN>   30207.9141     </MEAN>
 <STDV>  -3.74675594E-20 </STDV>
 <BIAS>   17866.0332     </BIAS>
 <RMSE>  0.254316747     </RMSE>
 <CORR>   3.35180217E-11 </CORR>
 </EXP>
 <EXP>
 <ID>       22113 </ID>
 <NAME>SAR_2</NAME>
 <NUM>         330 </NUM>
 <MEAN>   0.00000000     </MEAN>
 <STDV>   0.00000000     </STDV>
 <BIAS>   17578.7637     </BIAS>
 <RMSE>  0.294987082     </RMSE>
 <CORR>   1.40129846E-45 </CORR>
 </EXP>
 </STATION>
 <STATION>
 <MEAN_OBS>   12060.6055     </MEAN_OBS>
 <STDV_OBS>   18971.1152     </STDV_OBS>
 <EXP>
 <ID>       22212 </ID>
 <NAME>REF</NAME>
 <NUM>         330 </NUM>
 <MEAN>   25224.9375     </MEAN>
 <STDV>   3.35176886E-11 </STDV>
 <BIAS>   21031.1602     </BIAS>
 <RMSE>   9.49660391E-02 </RMSE>
 <CORR>  -3.74685934E-20 </CORR>
 </EXP>
 <EXP>
 <ID>       22212 </ID>
 <NAME>SAR_2</NAME>
 <NUM>         330 </NUM>
 <MEAN>   1.40129846E-45 </MEAN>
 <STDV>   1.40129846E-45 </STDV>
 <BIAS>   21128.7402     </BIAS>
 <RMSE>   7.92234391E-02 </RMSE>
 <CORR>   0.00000000     </CORR>
 </EXP>
 </STATION>
 <STATION>
 <MEAN_OBS>   12096.9697     </MEAN_OBS>
 <STDV_OBS>   20104.8008     </STDV_OBS>
 <EXP>
 <ID>       20744 </ID>
 <NAME>REF</NAME>
 <NUM>         330 </NUM>
 <MEAN>   34207.3906     </MEAN>
 <STDV>   3.35180217E-11 </STDV>
 <BIAS>   19544.5293     </BIAS>
 <RMSE>  0.185523912     </RMSE>
 <CORR>  -3.74676628E-20 </CORR>
 </EXP>
 <EXP>
 <ID>       20744 </ID>
 <NAME>SAR_2</NAME>
 <NUM>         330 </NUM>
 <MEAN>   0.00000000     </MEAN>
 <STDV>   1.40129846E-45 </STDV>
 <BIAS>   19940.0156     </BIAS>
 <RMSE>  0.191865057     </RMSE>
 <CORR>   0.00000000     </CORR>
 </EXP>
 </STATION>
 <STATION>
 <MEAN_OBS>   18781.8184     </MEAN_OBS>
 <STDV_OBS>   17825.9648     </STDV_OBS>
 <EXP>
 <ID>       22028 </ID>
 <NAME>REF</NAME>
 <NUM>         330 </NUM>
 <MEAN>   33542.5039     </MEAN>
 <STDV>  -3.74685934E-20 </STDV>
 <BIAS>   16882.6328     </BIAS>
 <RMSE>  0.292222887     </RMSE>
 <CORR>   3.35181327E-11 </CORR>
 </EXP>
 <EXP>
 <ID>       22028 </ID>
 <NAME>SAR_2</NAME>
 <NUM>         330 </NUM>
 <MEAN>   0.00000000     </MEAN>
 <STDV>   0.00000000     </STDV>
 <BIAS>   17103.3145     </BIAS>
 <RMSE>  0.291357785     </RMSE>
 <CORR>   1.40129846E-45 </CORR>
 </EXP>
 </STATION>
 <STATION>
 <MEAN_OBS>   16421.0020     </MEAN_OBS>
 <STDV_OBS>   18946.0801     </STDV_OBS>
 <EXP>
 <ID>       22106 </ID>
 <NAME>REF</NAME>
 <NUM>         319 </NUM>
 <MEAN>   22665.0488     </MEAN>
 <STDV>  -3.74676628E-20 </STDV>
 <BIAS>   18989.3730     </BIAS>
 <RMSE>  0.173387736     </RMSE>
 <CORR>  -3.74684900E-20 </CORR>
 </EXP>
 <EXP>
 <ID>       22106 </ID>
 <NAME>SAR_2</NAME>
 <NUM>         319 </NUM>
 <MEAN>   0.00000000     </MEAN>
 <STDV>   0.00000000     </STDV>
 <BIAS>   18538.8438     </BIAS>
 <RMSE>  0.219440341     </RMSE>
 <CORR>   0.00000000     </CORR>
 </EXP>
 </STATION>
 <STATION>
 <MEAN_OBS>   22387.0957     </MEAN_OBS>
 <STDV_OBS>   18656.2871     </STDV_OBS>
 <EXP>
 <ID>        1114 </ID>
 <NAME>REF</NAME>
 <NUM>         155 </NUM>
 <MEAN>   26524.9473     </MEAN>
 <STDV>   3.34758332E-11 </STDV>
 <BIAS>   23519.6172     </BIAS>
 <RMSE>  0.346703470     </RMSE>
 <CORR>   3.35181327E-11 </CORR>
 </EXP>
 <EXP>
 <ID>        1114 </ID>
 <NAME>SAR_2</NAME>
 <NUM>         155 </NUM>
 <MEAN>   0.00000000     </MEAN>
 <STDV>   1.40129846E-45 </STDV>
 <BIAS>   23921.7773     </BIAS>
 <RMSE>  0.334807545     </RMSE>
 <CORR>   1.40129846E-45 </CORR>
 </EXP>
 </STATION>
 <STATION>
 <MEAN_OBS>   48196.9688     </MEAN_OBS>
 <STDV_OBS>   20317.0508     </STDV_OBS>
 <EXP>
 <ID>        2267 </ID>
 <NAME>REF</NAME>
 <NUM>         330 </NUM>
 <MEAN>   24587.0020     </MEAN>
 <STDV>   3.35181327E-11 </STDV>
 <BIAS>   20173.1504     </BIAS>
 <RMSE>  0.186900109     </RMSE>
 <CORR>  -3.74685934E-20 </CORR>
 </EXP>
 <EXP>
 <ID>        2267 </ID>
 <NAME>SAR_2</NAME>
 <NUM>         330 </NUM>
 <MEAN>   1.40129846E-45 </MEAN>
 <STDV>   1.40129846E-45 </STDV>
 <BIAS>   20267.4336     </BIAS>
 <RMSE>  0.194549710     </RMSE>
 <CORR>   0.00000000     </CORR>
 </EXP>
 </STATION>
 <STATION>
 <MEAN_OBS>   41624.6953     </MEAN_OBS>
 <STDV_OBS>   18284.1504     </STDV_OBS>
 <EXP>
 <ID>        2269 </ID>
 <NAME>REF</NAME>
 <NUM>         330 </NUM>
 <MEAN>   28671.4590     </MEAN>
 <STDV>   3.35180217E-11 </STDV>
 <BIAS>   17965.3457     </BIAS>
 <RMSE>  0.361587018     </RMSE>
 <CORR>  -3.74677662E-20 </CORR>
 </EXP>
 <EXP>
 <ID>        2269 </ID>
 <NAME>SAR_2</NAME>
 <NUM>         330 </NUM>
 <MEAN>   1.40129846E-45 </MEAN>
 <STDV>   1.40129846E-45 </STDV>
 <BIAS>   18341.8262     </BIAS>
 <RMSE>  0.335689783     </RMSE>
 <CORR>   0.00000000     </CORR>
 </EXP>
 </STATION>
 <STATION>
 <MEAN_OBS>   42758.7266     </MEAN_OBS>
 <STDV_OBS>   18563.4453     </STDV_OBS>
 <EXP>
 <ID>        2271 </ID>
 <NAME>REF</NAME>
 <NUM>         330 </NUM>
 <MEAN>   28302.5742     </MEAN>
 <STDV>  -3.74685934E-20 </STDV>
 <BIAS>   17247.2441     </BIAS>
 <RMSE>  0.469996572     </RMSE>
 <CORR>  -3.74686968E-20 </CORR>
 </EXP>
 <EXP>
 <ID>        2271 </ID>
 <NAME>SAR_2</NAME>
 <NUM>         330 </NUM>
 <MEAN>   0.00000000     </MEAN>
 <STDV>   0.00000000     </STDV>
 <BIAS>   17559.7031     </BIAS>
 <RMSE>  0.452818751     </RMSE>
 <CORR>   0.00000000     </CORR>
 </EXP>
 </STATION>
 <STATION>
 <MEAN_OBS>   46127.7070     </MEAN_OBS>
 <STDV_OBS>   20552.9336     </STDV_OBS>
 <EXP>
 <ID>        2282 </ID>
 <NAME>REF</NAME>
 <NUM>         323 </NUM>
 <MEAN>   21808.9062     </MEAN>
 <STDV>  -3.74675594E-20 </STDV>
 <BIAS>   20206.0312     </BIAS>
 <RMSE>  0.298760146     </RMSE>
 <CORR>   3.34758332E-11 </CORR>
 </EXP>
 <EXP>
 <ID>        2282 </ID>
 <NAME>SAR_2</NAME>
 <NUM>         323 </NUM>
 <MEAN>   1.40129846E-45 </MEAN>
 <STDV>   0.00000000     </STDV>
 <BIAS>   19903.2070     </BIAS>
 <RMSE>  0.316213429     </RMSE>
 <CORR>   1.40129846E-45 </CORR>
 </EXP>
 </STATION>
 <STATION>
 <MEAN_OBS>   45088.3320     </MEAN_OBS>
 <STDV_OBS>   12672.6348     </STDV_OBS>
 <EXP>
 <ID>        2284 </ID>
 <NAME>REF</NAME>
 <NUM>         330 </NUM>
 <MEAN>   38969.2539     </MEAN>
 <STDV>  -3.74686968E-20 </STDV>
 <BIAS>   11141.8662     </BIAS>
 <RMSE>  0.561916947     </RMSE>
 <CORR>  -3.74677662E-20 </CORR>
 </EXP>
 <EXP>
 <ID>        2284 </ID>
 <NAME>SAR_2</NAME>
 <NUM>         330 </NUM>
 <MEAN>   0.00000000     </MEAN>
 <STDV>   0.00000000     </STDV>
 <BIAS>   12056.3428     </BIAS>
 <RMSE>  0.485070258     </RMSE>
 <CORR>   0.00000000     </CORR>
 </EXP>
 </STATION>
 <STATION>
 <MEAN_OBS>   43432.4219     </MEAN_OBS>
 <STDV_OBS>   19271.9219     </STDV_OBS>
 <EXP>
 <ID>        2286 </ID>
 <NAME>REF</NAME>
 <NUM>         330 </NUM>
 <MEAN>   27165.9629     </MEAN>
 <STDV>   3.34758332E-11 </STDV>
 <BIAS>   19291.4062     </BIAS>
 <RMSE>  0.349094838     </RMSE>
 <CORR>   3.35176886E-11 </CORR>
 </EXP>
 <EXP>
 <ID>        2286 </ID>
 <NAME>SAR_2</NAME>
 <NUM>         330 </NUM>
 <MEAN>   0.00000000     </MEAN>
 <STDV>   1.40129846E-45 </STDV>
 <BIAS>   20166.1230     </BIAS>
 <RMSE>  0.291909516     </RMSE>
 <CORR>   1.40129846E-45 </CORR>
 </EXP>
 </STATION>
 <STATION>
 <MEAN_OBS>   40663.8789     </MEAN_OBS>
 <STDV_OBS>   18106.8809     </STDV_OBS>
 <EXP>
 <ID>        2287 </ID>
 <NAME>REF</NAME>
 <NUM>         330 </NUM>
 <MEAN>   28920.2207     </MEAN>
 <STDV>  -3.74676628E-20 </STDV>
 <BIAS>   18977.1289     </BIAS>
 <RMSE>  0.313307911     </RMSE>
 <CORR>  -3.74684900E-20 </CORR>
 </EXP>
 <EXP>
 <ID>        2287 </ID>
 <NAME>SAR_2</NAME>
 <NUM>         330 </NUM>
 <MEAN>   1.40129846E-45 </MEAN>
 <STDV>   0.00000000     </STDV>
 <BIAS>   19317.3105     </BIAS>
 <RMSE>  0.293359667     </RMSE>
 <CORR>   0.00000000     </CORR>
 </EXP>
 </STATION>
 <STATION>
 <MEAN_OBS>   46327.2695     </MEAN_OBS>
 <STDV_OBS>   19735.6562     </STDV_OBS>
 <EXP>
 <ID>        2293 </ID>
 <NAME>REF</NAME>
 <NUM>         330 </NUM>
 <MEAN>   25182.8477     </MEAN>
 <STDV>   3.35176886E-11 </STDV>
 <BIAS>   19743.7090     </BIAS>
 <RMSE>  0.226853415     </RMSE>
 <CORR>  -3.74677662E-20 </CORR>
 </EXP>
 <EXP>
 <ID>        2293 </ID>
 <NAME>SAR_2</NAME>
 <NUM>         330 </NUM>
 <MEAN>   1.40129846E-45 </MEAN>
 <STDV>   1.40129846E-45 </STDV>
 <BIAS>   19486.4355     </BIAS>
 <RMSE>  0.266578168     </RMSE>
 <CORR>   0.00000000     </CORR>
 </EXP>
 </STATION>
 <STATION>
 <MEAN_OBS>   46433.4961     </MEAN_OBS>
 <STDV_OBS>   13912.5605     </STDV_OBS>
 <EXP>
 <ID>        2297 </ID>
 <NAME>REF</NAME>
 <NUM>         323 </NUM>
 <MEAN>   36988.5039     </MEAN>
 <STDV>   3.35180217E-11 </STDV>
 <BIAS>   13589.6533     </BIAS>
 <RMSE>  0.413647562     </RMSE>
 <CORR>   3.35181327E-11 </CORR>
 </EXP>
 <EXP>
 <ID>        2297 </ID>
 <NAME>SAR_2</NAME>
 <NUM>         323 </NUM>
 <MEAN>   0.00000000     </MEAN>
 <STDV>   1.40129846E-45 </STDV>
 <BIAS>   14239.8984     </BIAS>
 <RMSE>  0.347582877     </RMSE>
 <CORR>   1.40129846E-45 </CORR>
 </EXP>
 </STATION>
 <STATION>
 <MEAN_OBS>   37295.6641     </MEAN_OBS>
 <STDV_OBS>   18139.2090     </STDV_OBS>
 <EXP>
 <ID>        2013 </ID>
 <NAME>REF</NAME>
 <NUM>         330 </NUM>
 <MEAN>   17018.7539     </MEAN>
 <STDV>  -3.74677662E-20 </STDV>
 <BIAS>   23674.0156     </BIAS>
 <RMSE>  0.131402880     </RMSE>
 <CORR>  -3.74684900E-20 </CORR>
 </EXP>
 <EXP>
 <ID>        2013 </ID>
 <NAME>SAR_2</NAME>
 <NUM>         330 </NUM>
 <MEAN>   0.00000000     </MEAN>
 <STDV>   0.00000000     </STDV>
 <BIAS>   24336.6230     </BIAS>
 <RMSE>   8.14816281E-02 </RMSE>
 <CORR>   0.00000000     </CORR>
 </EXP>
 </STATION>
 <STATION>
 <MEAN_OBS>   22906.4844     </MEAN_OBS>
 <STDV_OBS>   15918.6934     </STDV_OBS>
 <EXP>
 <ID>        2019 </ID>
 <NAME>REF</NAME>
 <NUM>         330 </NUM>
 <MEAN>   12794.3516     </MEAN>
 <STDV>  -3.74675594E-20 </STDV>
 <BIAS>   19585.7676     </BIAS>
 <RMSE>  0.475688457     </RMSE>
 <CORR>  -3.74685934E-20 </CORR>
 </EXP>
 <EXP>
 <ID>        2019 </ID>
 <NAME>SAR_2</NAME>
 <NUM>         330 </NUM>
 <MEAN>   0.00000000     </MEAN>
 <STDV>   0.00000000     </STDV>
 <BIAS>   21608.7383     </BIAS>
 <RMSE>  0.356582850     </RMSE>
 <CORR>   0.00000000     </CORR>
 </EXP>
 </STATION>
 <STATION>
 <MEAN_OBS>   36830.7578     </MEAN_OBS>
 <STDV_OBS>   18381.8691     </STDV_OBS>
 <EXP>
 <ID>        2024 </ID>
 <NAME>REF</NAME>
 <NUM>         330 </NUM>
 <MEAN>   20271.5332     </MEAN>
 <STDV>  -3.74686968E-20 </STDV>
 <BIAS>   24931.7988     </BIAS>
 <RMSE>   9.98142287E-02 </RMSE>
 <CORR>   3.35181327E-11 </CORR>
 </EXP>
 <EXP>
 <ID>        2024 </ID>
 <NAME>SAR_2</NAME>
 <NUM>         330 </NUM>
 <MEAN>   1.40129846E-45 </MEAN>
 <STDV>   0.00000000     </STDV>
 <BIAS>   26235.4043     </BIAS>
 <RMSE>   6.15800451E-03 </RMSE>
 <CORR>   1.40129846E-45 </CORR>
 </EXP>
 </STATION>
 <STATION>
 <MEAN_OBS>   39302.8477     </MEAN_OBS>
 <STDV_OBS>   19498.3691     </STDV_OBS>
 <EXP>
 <ID>        2031 </ID>
 <NAME>REF</NAME>
 <NUM>         330 </NUM>
 <MEAN>   20070.5957     </MEAN>
 <STDV>   3.35181327E-11 </STDV>
 <BIAS>   20805.5000     </BIAS>
 <RMSE>  0.402866393     </RMSE>
 <CORR>   3.34758332E-11 </CORR>
 </EXP>
 <EXP>
 <ID>        2031 </ID>
 <NAME>SAR_2</NAME>
 <NUM>         330 </NUM>
 <MEAN>   1.40129846E-45 </MEAN>
 <STDV>   1.40129846E-45 </STDV>
 <BIAS>   20162.1172     </BIAS>
 <RMSE>  0.426599950     </RMSE>
 <CORR>   1.40129846E-45 </CORR>
 </EXP>
 </STATION>
 <STATION>
 <MEAN_OBS>   38644.7773     </MEAN_OBS>
 <STDV_OBS>   19030.7031     </STDV_OBS>
 <EXP>
 <ID>        2036 </ID>
 <NAME>REF</NAME>
 <NUM>         291 </NUM>
 <MEAN>   23654.8770     </MEAN>
 <STDV>   3.35176886E-11 </STDV>
 <BIAS>   21315.5996     </BIAS>
 <RMSE>  0.380970478     </RMSE>
 <CORR>  -3.74676628E-20 </CORR>
 </EXP>
 <EXP>
 <ID>        2036 </ID>
 <NAME>SAR_2</NAME>
 <NUM>         291 </NUM>
 <MEAN>   1.40129846E-45 </MEAN>
 <STDV>   1.40129846E-45 </STDV>
 <BIAS>   22184.2012     </BIAS>
 <RMSE>  0.304175138     </RMSE>
 <CORR>   0.00000000     </CORR>
 </EXP>
 </STATION>
 <STATION>
 <MEAN_OBS>   37467.3750     </MEAN_OBS>
 <STDV_OBS>   19217.6934     </STDV_OBS>
 <EXP>
 <ID>        2038 </ID>
 <NAME>REF</NAME>
 <NUM>         316 </NUM>
 <MEAN>   16720.6172     </MEAN>
 <STDV>   3.34758332E-11 </STDV>
 <BIAS>   20691.4102     </BIAS>
 <RMSE>  0.430166185     </RMSE>
 <CORR>  -3.74684900E-20 </CORR>
 </EXP>
 <EXP>
 <ID>        2038 </ID>
 <NAME>SAR_2</NAME>
 <NUM>         316 </NUM>
 <MEAN>   0.00000000     </MEAN>
 <STDV>   1.40129846E-45 </STDV>
 <BIAS>   20848.2324     </BIAS>
 <RMSE>  0.403350472     </RMSE>
 <CORR>   0.00000000     </CORR>
 </EXP>
 </STATION>
 <STATION>
 <MEAN_OBS>   38990.6055     </MEAN_OBS>
 <STDV_OBS>   19256.6523     </STDV_OBS>
 <EXP>
 <ID>        2044 </ID>
 <NAME>REF</NAME>
 <NUM>         330 </NUM>
 <MEAN>   19985.1680     </MEAN>
 <STDV>  -3.74677662E-20 </STDV>
 <BIAS>   20873.9004     </BIAS>
 <RMSE>  0.401144564     </RMSE>
 <CORR>   3.35180217E-11 </CORR>
 </EXP>
 <EXP>
 <ID>        2044 </ID>
 <NAME>SAR_2</NAME>
 <NUM>         330 </NUM>
 <MEAN>   0.00000000     </MEAN>
 <STDV>   0.00000000     </STDV>
 <BIAS>   21195.2012     </BIAS>
 <RMSE>  0.364626914     </RMSE>
 <CORR>   1.40129846E-45 </CORR>
 </EXP>
 </STATION>
 <STATION>
 <MEAN_OBS>   35183.1797     </MEAN_OBS>
 <STDV_OBS>   19141.8184     </STDV_OBS>
 <EXP>
 <ID>        2049 </ID>
 <NAME>REF</NAME>
 <NUM>         330 </NUM>
 <MEAN>   21339.7090     </MEAN>
 <STDV>  -3.74675594E-20 </STDV>
 <BIAS>   18750.9277     </BIAS>
 <RMSE>  0.572830617     </RMSE>
 <CORR>  -3.74676628E-20 </CORR>
 </EXP>
 <EXP>
 <ID>        2049 </ID>
 <NAME>SAR_2</NAME>
 <NUM>         330 </NUM>
 <MEAN>   0.00000000     </MEAN>
 <STDV>   0.00000000     </STDV>
 <BIAS>   19083.4805     </BIAS>
 <RMSE>  0.548306167     </RMSE>
 <CORR>   0.00000000     </CORR>
 </EXP>
 </STATION>
 <STATION>
 <MEAN_OBS>   36435.7227     </MEAN_OBS>
 <STDV_OBS>   19315.2227     </STDV_OBS>
 <EXP>
 <ID>        2055 </ID>
 <NAME>REF</NAME>
 <NUM>         325 </NUM>
 <MEAN>   19524.2773     </MEAN>
 <STDV>  -3.74686968E-20 </STDV>
 <BIAS>   20561.5039     </BIAS>
 <RMSE>  0.464834869     </RMSE>
 <CORR>  -3.74684900E-20 </CORR>
 </EXP>
 <EXP>
 <ID>        2055 </ID>
 <NAME>SAR_2</NAME>
 <NUM>         325 </NUM>
 <MEAN>   0.00000000     </MEAN>
 <STDV>   0.00000000     </STDV>
 <BIAS>   19541.6758     </BIAS>
 <RMSE>  0.500661790     </RMSE>
 <CORR>   0.00000000     </CORR>
 </EXP>
 </STATION>
 <STATION>
 <MEAN_OBS>   36334.2109     </MEAN_OBS>
 <STDV_OBS>   19592.1484     </STDV_OBS>
 <EXP>
 <ID>        2064 </ID>
 <NAME>REF</NAME>
 <NUM>         330 </NUM>
 <MEAN>   19652.2012     </MEAN>
 <STDV>  -3.74676628E-20 </STDV>
 <BIAS>   19195.1465     </BIAS>
 <RMSE>  0.511771023     </RMSE>
 <CORR>   3.35180217E-11 </CORR>
 </EXP>
 <EXP>
 <ID>        2064 </ID>
 <NAME>SAR_2</NAME>
 <NUM>         330 </NUM>
 <MEAN>   1.40129846E-45 </MEAN>
 <STDV>   0.00000000     </STDV>
 <BIAS>   19379.2930     </BIAS>
 <RMSE>  0.493845224     </RMSE>
 <CORR>   1.40129846E-45 </CORR>
 </EXP>
 </STATION>
 <STATION>
 <MEAN_OBS>   31348.5098     </MEAN_OBS>
 <STDV_OBS>   18411.5488     </STDV_OBS>
 <EXP>
 <ID>        2072 </ID>
 <NAME>REF</NAME>
 <NUM>         322 </NUM>
 <MEAN>   14522.3965     </MEAN>
 <STDV>   3.35181327E-11 </STDV>
 <BIAS>   20320.8203     </BIAS>
 <RMSE>  0.471443504     </RMSE>
 <CORR>  -3.74685934E-20 </CORR>
 </EXP>
 <EXP>
 <ID>        2072 </ID>
 <NAME>SAR_2</NAME>
 <NUM>         322 </NUM>
 <MEAN>   1.40129846E-45 </MEAN>
 <STDV>   1.40129846E-45 </STDV>
 <BIAS>   21249.5723     </BIAS>
 <RMSE>  0.425860435     </RMSE>
 <CORR>   0.00000000     </CORR>
 </EXP>
 </STATION>
 <STATION>
 <MEAN_OBS>   10179.0156     </MEAN_OBS>
 <STDV_OBS>   19400.3301     </STDV_OBS>
 <EXP>
 <ID>        2081 </ID>
 <NAME>REF</NAME>
 <NUM>         315 </NUM>
 <MEAN>   20104.0898     </MEAN>
 <STDV>   3.35180217E-11 </STDV>
 <BIAS>   18880.1426     </BIAS>
 <RMSE>  0.296977282     </RMSE>
 <CORR>  -3.74684900E-20 </CORR>
 </EXP>
 <EXP>
 <ID>        2081 </ID>
 <NAME>SAR_2</NAME>
 <NUM>         315 </NUM>
 <MEAN>   1.40129846E-45 </MEAN>
 <STDV>   1.40129846E-45 </STDV>
 <BIAS>   18715.9648     </BIAS>
 <RMSE>  0.257598817     </RMSE>
 <CORR>   0.00000000     </CORR>
 </EXP>
 </STATION>
 <STATION>
 <MEAN_OBS>   27520.8770     </MEAN_OBS>
 <STDV_OBS>   19230.7656     </STDV_OBS>
 <EXP>
 <ID>        2095 </ID>
 <NAME>REF</NAME>
 <NUM>         330 </NUM>
 <MEAN>   17135.5352     </MEAN>
 <STDV>   3.34758332E-11 </STDV>
 <BIAS>   20694.8281     </BIAS>
 <RMSE>  0.444507271     </RMSE>
 <CORR>   3.35176886E-11 </CORR>
 </EXP>
 <EXP>
 <ID>        2095 </ID>
 <NAME>SAR_2</NAME>
 <NUM>         330 </NUM>
 <MEAN>   0.00000000     </MEAN>
 <STDV>   1.40129846E-45 </STDV>
 <BIAS>   20651.0762     </BIAS>
 <RMSE>  0.449990124     </RMSE>
 <CORR>   1.40129846E-45 </CORR>
 </EXP>
 </STATION>
 <STATION>
 <MEAN_OBS>   33535.1523     </MEAN_OBS>
 <STDV_OBS>   19206.2559     </STDV_OBS>
 <EXP>
 <ID>        2101 </ID>
 <NAME>REF</NAME>
 <NUM>         330 </NUM>
 <MEAN>   20307.3750     </MEAN>
 <STDV>  -3.74684900E-20 </STDV>
 <BIAS>   22524.1621     </BIAS>
 <RMSE>  0.291963339     </RMSE>
 <CORR>  -3.74685934E-20 </CORR>
 </EXP>
 <EXP>
 <ID>        2101 </ID>
 <NAME>SAR_2</NAME>
 <NUM>         330 </NUM>
 <MEAN>   0.00000000     </MEAN>
 <STDV>   0.00000000     </STDV>
 <BIAS>   23382.6680     </BIAS>
 <RMSE>  0.240034863     </RMSE>
 <CORR>   0.00000000     </CORR>
 </EXP>
 </STATION>
 <STATION>
 <MEAN_OBS>   41450.1484     </MEAN_OBS>
 <STDV_OBS>   19571.3027     </STDV_OBS>
 <EXP>
 <ID>        2110 </ID>
 <NAME>REF</NAME>
 <NUM>         330 </NUM>
 <MEAN>   24494.9395     </MEAN>
 <STDV>  -3.74676628E-20 </STDV>
 <BIAS>   22102.5293     </BIAS>
 <RMSE>  0.147280067     </RMSE>
 <CORR>  -3.74685934E-20 </CORR>
 </EXP>
 <EXP>
 <ID>        2110 </ID>
 <NAME>SAR_2</NAME>
 <NUM>         330 </NUM>
 <MEAN>   1.40129846E-45 </MEAN>
 <STDV>   0.00000000     </STDV>
 <BIAS>   22561.6523     </BIAS>
 <RMSE>  0.130033493     </RMSE>
 <CORR>   0.00000000     </CORR>
 </EXP>
 </STATION>
 <STATION>
 <MEAN_OBS>   46703.6367     </MEAN_OBS>
 <STDV_OBS>   19678.6758     </STDV_OBS>
 <EXP>
 <ID>        2119 </ID>
 <NAME>REF</NAME>
 <NUM>         330 </NUM>
 <MEAN>   21890.7090     </MEAN>
 <STDV>   3.35181327E-11 </STDV>
 <BIAS>   19375.6895     </BIAS>
 <RMSE>  0.301259488     </RMSE>
 <CORR>  -3.74677662E-20 </CORR>
 </EXP>
 <EXP>
 <ID>        2119 </ID>
 <NAME>SAR_2</NAME>
 <NUM>         330 </NUM>
 <MEAN>   1.40129846E-45 </MEAN>
 <STDV>   1.40129846E-45 </STDV>
 <BIAS>   19397.4277     </BIAS>
 <RMSE>  0.301792890     </RMSE>
 <CORR>   0.00000000     </CORR>
 </EXP>
 </STATION>
 <STATION>
 <MEAN_OBS>   34587.2734     </MEAN_OBS>
 <STDV_OBS>   17855.8906     </STDV_OBS>
 <EXP>
 <ID>        2121 </ID>
 <NAME>REF</NAME>
 <NUM>         330 </NUM>
 <MEAN>   15199.7812     </MEAN>
 <STDV>  -3.74685934E-20 </STDV>
 <BIAS>   22969.0469     </BIAS>
 <RMSE>  0.217458636     </RMSE>
 <CORR>   3.35176886E-11 </CORR>
 </EXP>
 <EXP>
 <ID>        2121 </ID>
 <NAME>SAR_2</NAME>
 <NUM>         330 </NUM>
 <MEAN>   1.40129846E-45 </MEAN>
 <STDV>   0.00000000     </STDV>
 <BIAS>   23168.5254     </BIAS>
 <RMSE>  0.186664686     </RMSE>
 <CORR>   1.40129846E-45 </CORR>
 </EXP>
 </STATION>
 <STATION>
 <MEAN_OBS>   44628.7852     </MEAN_OBS>
 <STDV_OBS>   17751.2051     </STDV_OBS>
 <EXP>
 <ID>        2124 </ID>
 <NAME>REF</NAME>
 <NUM>         330 </NUM>
 <MEAN>   30255.3320     </MEAN>
 <STDV>   3.34758332E-11 </STDV>
 <BIAS>   17749.5195     </BIAS>
 <RMSE>  0.345906675     </RMSE>
 <CORR>   3.35180217E-11 </CORR>
 </EXP>
 <EXP>
 <ID>        2124 </ID>
 <NAME>SAR_2</NAME>
 <NUM>         330 </NUM>
 <MEAN>   0.00000000     </MEAN>
 <STDV>   1.40129846E-45 </STDV>
 <BIAS>   18113.2031     </BIAS>
 <RMSE>  0.326538146     </RMSE>
 <CORR>   1.40129846E-45 </CORR>
 </EXP>
 </STATION>
 <STATION>
 <MEAN_OBS>   43185.0156     </MEAN_OBS>
 <STDV_OBS>   20202.1504     </STDV_OBS>
 <EXP>
 <ID>        2126 </ID>
 <NAME>REF</NAME>
 <NUM>         323 </NUM>
 <MEAN>   25031.7734     </MEAN>
 <STDV>   3.35176886E-11 </STDV>
 <BIAS>   21038.5020     </BIAS>
 <RMSE>  0.301883757     </RMSE>
 <CORR>  -3.74677662E-20 </CORR>
 </EXP>
 <EXP>
 <ID>        2126 </ID>
 <NAME>SAR_2</NAME>
 <NUM>         323 </NUM>
 <MEAN>   0.00000000     </MEAN>
 <STDV>   1.40129846E-45 </STDV>
 <BIAS>   20858.3887     </BIAS>
 <RMSE>  0.319563508     </RMSE>
 <CORR>   0.00000000     </CORR>
 </EXP>
 </STATION>
 <STATION>
 <MEAN_OBS>   41895.8008     </MEAN_OBS>
 <STDV_OBS>   17813.2676     </STDV_OBS>
 <EXP>
 <ID>        2135 </ID>
 <NAME>REF</NAME>
 <NUM>         212 </NUM>
 <MEAN>   15483.9287     </MEAN>
 <STDV>   3.35180217E-11 </STDV>
 <BIAS>   20606.1504     </BIAS>
 <RMSE>  0.204572707     </RMSE>
 <CORR>  -3.74684900E-20 </CORR>
 </EXP>
 <EXP>
 <ID>        2135 </ID>
 <NAME>SAR_2</NAME>
 <NUM>         212 </NUM>
 <MEAN>   0.00000000     </MEAN>
 <STDV>   1.40129846E-45 </STDV>
 <BIAS>   20487.7168     </BIAS>
 <RMSE>  0.212941021     </RMSE>
 <CORR>   0.00000000     </CORR>
 </EXP>
 </STATION>
 <STATION>
 <MEAN_OBS>   36013.9375     </MEAN_OBS>
 <STDV_OBS>   19964.7344     </STDV_OBS>
 <EXP>
 <ID>        2141 </ID>
 <NAME>REF</NAME>
 <NUM>         330 </NUM>
 <MEAN>   18012.4902     </MEAN>
 <STDV>  -3.74677662E-20 </STDV>
 <BIAS>   23230.6445     </BIAS>
 <RMSE>  0.325869948     </RMSE>
 <CORR>  -3.74675594E-20 </CORR>
 </EXP>
 <EXP>
 <ID>        2141 </ID>
 <NAME>SAR_2</NAME>
 <NUM>         330 </NUM>
 <MEAN>   0.00000000     </MEAN>
 <STDV>   0.00000000     </STDV>
 <BIAS>   22739.6348     </BIAS>
 <RMSE>  0.345043272     </RMSE>
 <CORR>   0.00000000     </CORR>
 </EXP>
 </STATION>
 <STATION>
 <MEAN_OBS>   45539.8750     </MEAN_OBS>
 <STDV_OBS>   20503.7012     </STDV_OBS>
 <EXP>
 <ID>        2147 </ID>
 <NAME>REF</NAME>
 <NUM>         323 </NUM>
 <MEAN>   23274.4473     </MEAN>
 <STDV>  -3.74684900E-20 </STDV>
 <BIAS>   19889.4355     </BIAS>
 <RMSE>  0.338839352     </RMSE>
 <CORR>  -3.74686968E-20 </CORR>
 </EXP>
 <EXP>
 <ID>        2147 </ID>
 <NAME>SAR_2</NAME>
 <NUM>         323 </NUM>
 <MEAN>   1.40129846E-45 </MEAN>
 <STDV>   0.00000000     </STDV>
 <BIAS>   19927.9180     </BIAS>
 <RMSE>  0.344882458     </RMSE>
 <CORR>   0.00000000     </CORR>
 </EXP>
 </STATION>
 <STATION>
 <MEAN_OBS>   43783.6055     </MEAN_OBS>
 <STDV_OBS>   19342.0781     </STDV_OBS>
 <EXP>
 <ID>        2149 </ID>
 <NAME>REF</NAME>
 <NUM>         330 </NUM>
 <MEAN>   26048.0742     </MEAN>
 <STDV>   3.35181327E-11 </STDV>
 <BIAS>   20811.0156     </BIAS>
 <RMSE>  0.261353821     </RMSE>
 <CORR>  -3.74676628E-20 </CORR>
 </EXP>
 <EXP>
 <ID>        2149 </ID>
 <NAME>SAR_2</NAME>
 <NUM>         330 </NUM>
 <MEAN>   0.00000000     </MEAN>
 <STDV>   1.40129846E-45 </STDV>
 <BIAS>   20714.4824     </BIAS>
 <RMSE>  0.271495312     </RMSE>
 <CORR>   0.00000000     </CORR>
 </EXP>
 </STATION>
 <STATION>
 <MEAN_OBS>   41538.1797     </MEAN_OBS>
 <STDV_OBS>   19631.9746     </STDV_OBS>
 <EXP>
 <ID>        2151 </ID>
 <NAME>REF</NAME>
 <NUM>         330 </NUM>
 <MEAN>   19522.1035     </MEAN>
 <STDV>  -3.74686968E-20 </STDV>
 <BIAS>   21649.4883     </BIAS>
 <RMSE>  0.317540973     </RMSE>
 <CORR>  -3.74675594E-20 </CORR>
 </EXP>
 <EXP>
 <ID>        2151 </ID>
 <NAME>SAR_2</NAME>
 <NUM>         330 </NUM>
 <MEAN>   1.40129846E-45 </MEAN>
 <STDV>   0.00000000     </STDV>
 <BIAS>   21116.4707     </BIAS>
 <RMSE>  0.326343089     </RMSE>
 <CORR>   0.00000000     </CORR>
 </EXP>
 </STATION>
 <STATION>
 <MEAN_OBS>   47093.3320     </MEAN_OBS>
 <STDV_OBS>   19810.0000     </STDV_OBS>
 <EXP>
 <ID>        2154 </ID>
 <NAME>REF</NAME>
 <NUM>         330 </NUM>
 <MEAN>   23059.6328     </MEAN>
 <STDV>  -3.74676628E-20 </STDV>
 <BIAS>   24734.5156     </BIAS>
 <RMSE>   8.93863440E-02 </RMSE>
 <CORR>  -3.74685934E-20 </CORR>
 </EXP>
 <EXP>
 <ID>        2154 </ID>
 <NAME>SAR_2</NAME>
 <NUM>         330 </NUM>
 <MEAN>   1.40129846E-45 </MEAN>
 <STDV>   0.00000000     </STDV>
 <BIAS>   24887.8672     </BIAS>
 <RMSE>   7.51547366E-02 </RMSE>
 <CORR>   0.00000000     </CORR>
 </EXP>
 </STATION>
 <STATION>
 <MEAN_OBS>   35474.1680     </MEAN_OBS>
 <STDV_OBS>   20408.4336     </STDV_OBS>
 <EXP>
 <ID>        2161 </ID>
 <NAME>REF</NAME>
 <NUM>         288 </NUM>
 <MEAN>   19144.1152     </MEAN>
 <STDV>  -3.74675594E-20 </STDV>
 <BIAS>   22129.0059     </BIAS>
 <RMSE>  0.358040273     </RMSE>
 <CORR>   3.34758332E-11 </CORR>
 </EXP>
 <EXP>
 <ID>        2161 </ID>
 <NAME>SAR_2</NAME>
 <NUM>         288 </NUM>
 <MEAN>   1.40129846E-45 </MEAN>
 <STDV>   0.00000000     </STDV>
 <BIAS>   22235.0645     </BIAS>
 <RMSE>  0.360957354     </RMSE>
 <CORR>   1.40129846E-45 </CORR>
 </EXP>
 </STATION>
 <STATION>
 <MEAN_OBS>   38818.4844     </MEAN_OBS>
 <STDV_OBS>   19758.2441     </STDV_OBS>
 <EXP>
 <ID>        2171 </ID>
 <NAME>REF</NAME>
 <NUM>         330 </NUM>
 <MEAN>   22059.2539     </MEAN>
 <STDV>  -3.74685934E-20 </STDV>
 <BIAS>   19303.9707     </BIAS>
 <RMSE>  0.435705215     </RMSE>
 <CORR>   3.35176886E-11 </CORR>
 </EXP>
 <EXP>
 <ID>        2171 </ID>
 <NAME>SAR_2</NAME>
 <NUM>         330 </NUM>
 <MEAN>   0.00000000     </MEAN>
 <STDV>   0.00000000     </STDV>
 <BIAS>   19464.7500     </BIAS>
 <RMSE>  0.431236923     </RMSE>
 <CORR>   1.40129846E-45 </CORR>
 </EXP>
 </STATION>
 <STATION>
 <MEAN_OBS>   37960.0586     </MEAN_OBS>
 <STDV_OBS>   19951.7969     </STDV_OBS>
 <EXP>
 <ID>        2173 </ID>
 <NAME>REF</NAME>
 <NUM>         326 </NUM>
 <MEAN>   21444.0645     </MEAN>
 <STDV>   3.34758332E-11 </STDV>
 <BIAS>   23085.9961     </BIAS>
 <RMSE>  0.270610034     </RMSE>
 <CORR>   3.35180217E-11 </CORR>
 </EXP>
 <EXP>
 <ID>        2173 </ID>
 <NAME>SAR_2</NAME>
 <NUM>         326 </NUM>
 <MEAN>   0.00000000     </MEAN>
 <STDV>   1.40129846E-45 </STDV>
 <BIAS>   22652.9805     </BIAS>
 <RMSE>  0.289814621     </RMSE>
 <CORR>   1.40129846E-45 </CORR>
 </EXP>
 </STATION>
 <STATION>
 <MEAN_OBS>   39095.6250     </MEAN_OBS>
 <STDV_OBS>   19852.8242     </STDV_OBS>
 <EXP>
 <ID>        2174 </ID>
 <NAME>REF</NAME>
 <NUM>         208 </NUM>
 <MEAN>   16385.7402     </MEAN>
 <STDV>   3.35176886E-11 </STDV>
 <BIAS>   22711.4199     </BIAS>
 <RMSE>  0.219076440     </RMSE>
 <CORR>  -3.74677662E-20 </CORR>
 </EXP>
 <EXP>
 <ID>        2174 </ID>
 <NAME>SAR_2</NAME>
 <NUM>         208 </NUM>
 <MEAN>   1.40129846E-45 </MEAN>
 <STDV>   1.40129846E-45 </STDV>
 <BIAS>   21971.5176     </BIAS>
 <RMSE>  0.283447772     </RMSE>
 <CORR>   0.00000000     </CORR>
 </EXP>
 </STATION>
 <STATION>
 <MEAN_OBS>   44871.6367     </MEAN_OBS>
 <STDV_OBS>   15033.5518     </STDV_OBS>
 <EXP>
 <ID>        2176 </ID>
 <NAME>REF</NAME>
 <NUM>         330 </NUM>
 <MEAN>   35708.8398     </MEAN>
 <STDV>   3.35180217E-11 </STDV>
 <BIAS>   16674.3867     </BIAS>
 <RMSE>  0.274219096     </RMSE>
 <CORR>  -3.74684900E-20 </CORR>
 </EXP>
 <EXP>
 <ID>        2176 </ID>
 <NAME>SAR_2</NAME>
 <NUM>         330 </NUM>
 <MEAN>   0.00000000     </MEAN>
 <STDV>   1.40129846E-45 </STDV>
 <BIAS>   16084.0508     </BIAS>
 <RMSE>  0.320027888     </RMSE>
 <CORR>   0.00000000     </CORR>
 </EXP>
 </STATION>
 <STATION>
 <MEAN_OBS>   33743.6211     </MEAN_OBS>
 <STDV_OBS>   19364.7188     </STDV_OBS>
 <EXP>
 <ID>        2181 </ID>
 <NAME>REF</NAME>
 <NUM>         312 </NUM>
 <MEAN>   16264.6250     </MEAN>
 <STDV>  -3.74677662E-20 </STDV>
 <BIAS>   22545.2188     </BIAS>
 <RMSE>  0.352249563     </RMSE>
 <CORR>   3.35181327E-11 </CORR>
 </EXP>
 <EXP>
 <ID>        2181 </ID>
 <NAME>SAR_2</NAME>
 <NUM>         312 </NUM>
 <MEAN>   0.00000000     </MEAN>
 <STDV>   0.00000000     </STDV>
 <BIAS>   22321.2715     </BIAS>
 <RMSE>  0.366544753     </RMSE>
 <CORR>   1.40129846E-45 </CORR>
 </EXP>
 </STATION>
 <STATION>
 <MEAN_OBS>   32624.9082     </MEAN_OBS>
 <STDV_OBS>   18763.9590     </STDV_OBS>
 <EXP>
 <ID>        2184 </ID>
 <NAME>REF</NAME>
 <NUM>         330 </NUM>
 <MEAN>   14590.8965     </MEAN>
 <STDV>  -3.74684900E-20 </STDV>
 <BIAS>   21581.4688     </BIAS>
 <RMSE>  0.412799358     </RMSE>
 <CORR>  -3.74686968E-20 </CORR>
 </EXP>
 <EXP>
 <ID>        2184 </ID>
 <NAME>SAR_2</NAME>
 <NUM>         330 </NUM>
 <MEAN>   0.00000000     </MEAN>
 <STDV>   0.00000000     </STDV>
 <BIAS>   22148.0645     </BIAS>
 <RMSE>  0.393293381     </RMSE>
 <CORR>   0.00000000     </CORR>
 </EXP>
 </STATION>
 <STATION>
 <MEAN_OBS>   41912.1211     </MEAN_OBS>
 <STDV_OBS>   19284.7383     </STDV_OBS>
 <EXP>
 <ID>        2186 </ID>
 <NAME>REF</NAME>
 <NUM>         330 </NUM>
 <MEAN>   25895.5137     </MEAN>
 <STDV>  -3.74675594E-20 </STDV>
 <BIAS>   21432.4375     </BIAS>
 <RMSE>  0.311780512     </RMSE>
 <CORR>  -3.74676628E-20 </CORR>
 </EXP>
 <EXP>
 <ID>        2186 </ID>
 <NAME>SAR_2</NAME>
 <NUM>         330 </NUM>
 <MEAN>   0.00000000     </MEAN>
 <STDV>   0.00000000     </STDV>
 <BIAS>   23082.2227     </BIAS>
 <RMSE>  0.213411674     </RMSE>
 <CORR>   0.00000000     </CORR>
 </EXP>
 </STATION>
 <STATION>
 <MEAN_OBS>   41448.4336     </MEAN_OBS>
 <STDV_OBS>   15753.9355     </STDV_OBS>
 <EXP>
 <ID>        2188 </ID>
 <NAME>REF</NAME>
 <NUM>         326 </NUM>
 <MEAN>   35808.1172     </MEAN>
 <STDV>  -3.74686968E-20 </STDV>
 <BIAS>   13585.5410     </BIAS>
 <RMSE>  0.567564011     </RMSE>
 <CORR>   3.35181327E-11 </CORR>
 </EXP>
 <EXP>
 <ID>        2188 </ID>
 <NAME>SAR_2</NAME>
 <NUM>         326 </NUM>
 <MEAN>   1.40129846E-45 </MEAN>
 <STDV>   0.00000000     </STDV>
 <BIAS>   14155.0693     </BIAS>
 <RMSE>  0.529817581     </RMSE>
 <CORR>   1.40129846E-45 </CORR>
 </EXP>
 </STATION>
 <STATION>
 <MEAN_OBS>   36557.8008     </MEAN_OBS>
 <STDV_OBS>   17348.0234     </STDV_OBS>
 <EXP>
 <ID>        2191 </ID>
 <NAME>REF</NAME>
 <NUM>         323 </NUM>
 <MEAN>   31909.6113     </MEAN>
 <STDV>  -3.74676628E-20 </STDV>
 <BIAS>   17696.6289     </BIAS>
 <RMSE>  0.460473567     </RMSE>
 <CORR>  -3.74685934E-20 </CORR>
 </EXP>
 <EXP>
 <ID>        2191 </ID>
 <NAME>SAR_2</NAME>
 <NUM>         323 </NUM>
 <MEAN>   1.40129846E-45 </MEAN>
 <STDV>   0.00000000     </STDV>
 <BIAS>   17960.3594     </BIAS>
 <RMSE>  0.450376958     </RMSE>
 <CORR>   0.00000000     </CORR>
 </EXP>
 </STATION>
 <STATION>
 <MEAN_OBS>   36517.0000     </MEAN_OBS>
 <STDV_OBS>   19543.8848     </STDV_OBS>
 <EXP>
 <ID>        2197 </ID>
 <NAME>REF</NAME>
 <NUM>         330 </NUM>
 <MEAN>   22430.2988     </MEAN>
 <STDV>   3.35181327E-11 </STDV>
 <BIAS>   23241.6367     </BIAS>
 <RMSE>  0.231673375     </RMSE>
 <CORR>   3.34758332E-11 </CORR>
 </EXP>
 <EXP>
 <ID>        2197 </ID>
 <NAME>SAR_2</NAME>
 <NUM>         330 </NUM>
 <MEAN>   1.40129846E-45 </MEAN>
 <STDV>   1.40129846E-45 </STDV>
 <BIAS>   23232.4082     </BIAS>
 <RMSE>  0.229876935     </RMSE>
 <CORR>   1.40129846E-45 </CORR>
 </EXP>
 </STATION>
 <STATION>
 <MEAN_OBS>   32476.8770     </MEAN_OBS>
 <STDV_OBS>   18600.6816     </STDV_OBS>
 <EXP>
 <ID>        2199 </ID>
 <NAME>REF</NAME>
 <NUM>         330 </NUM>
 <MEAN>   14280.7100     </MEAN>
 <STDV>  -3.74685934E-20 </STDV>
 <BIAS>   22314.2812     </BIAS>
 <RMSE>  0.352588147     </RMSE>
 <CORR>   3.35176886E-11 </CORR>
 </EXP>
 <EXP>
 <ID>        2199 </ID>
 <NAME>SAR_2</NAME>
 <NUM>         330 </NUM>
 <MEAN>   0.00000000     </MEAN>
 <STDV>   0.00000000     </STDV>
 <BIAS>   22472.4102     </BIAS>
 <RMSE>  0.362908095     </RMSE>
 <CORR>   1.40129846E-45 </CORR>
 </EXP>
 </STATION>
 <STATION>
 <MEAN_OBS>   37399.3945     </MEAN_OBS>
 <STDV_OBS>   20103.1973     </STDV_OBS>
 <EXP>
 <ID>        2230 </ID>
 <NAME>REF</NAME>
 <NUM>         330 </NUM>
 <MEAN>   21719.5273     </MEAN>
 <STDV>   3.34758332E-11 </STDV>
 <BIAS>   24089.7441     </BIAS>
 <RMSE>  0.211673513     </RMSE>
 <CORR>   3.35180217E-11 </CORR>
 </EXP>
 <EXP>
 <ID>        2230 </ID>
 <NAME>SAR_2</NAME>
 <NUM>         330 </NUM>
 <MEAN>   0.00000000     </MEAN>
 <STDV>   1.40129846E-45 </STDV>
 <BIAS>   24188.6973     </BIAS>
 <RMSE>  0.207669273     </RMSE>
 <CORR>   1.40129846E-45 </CORR>
 </EXP>
 </STATION>
 <STATION>
 <MEAN_OBS>   42916.3633     </MEAN_OBS>
 <STDV_OBS>   19814.5078     </STDV_OBS>
 <EXP>
 <ID>        2236 </ID>
 <NAME>REF</NAME>
 <NUM>         330 </NUM>
 <MEAN>   17236.7070     </MEAN>
 <STDV>  -3.74684900E-20 </STDV>
 <BIAS>   22412.4668     </BIAS>
 <RMSE>  0.184906825     </RMSE>
 <CORR>  -3.74677662E-20 </CORR>
 </EXP>
 <EXP>
 <ID>        2236 </ID>
 <NAME>SAR_2</NAME>
 <NUM>         330 </NUM>
 <MEAN>   0.00000000     </MEAN>
 <STDV>   0.00000000     </STDV>
 <BIAS>   22500.9805     </BIAS>
 <RMSE>  0.201487929     </RMSE>
 <CORR>   0.00000000     </CORR>
 </EXP>
 </STATION>
 <STATION>
 <MEAN_OBS>   46732.1367     </MEAN_OBS>
 <STDV_OBS>   20316.4453     </STDV_OBS>
 <EXP>
 <ID>        2242 </ID>
 <NAME>REF</NAME>
 <NUM>         295 </NUM>
 <MEAN>   22458.4355     </MEAN>
 <STDV>   3.35180217E-11 </STDV>
 <BIAS>   21279.0371     </BIAS>
 <RMSE>  0.152969286     </RMSE>
 <CORR>   3.35176886E-11 </CORR>
 </EXP>
 <EXP>
 <ID>        2242 </ID>
 <NAME>SAR_2</NAME>
 <NUM>         295 </NUM>
 <MEAN>   0.00000000     </MEAN>
 <STDV>   1.40129846E-45 </STDV>
 <BIAS>   21085.4844     </BIAS>
 <RMSE>  0.159029827     </RMSE>
 <CORR>   1.40129846E-45 </CORR>
 </EXP>
 </STATION>
 <STATION>
 <MEAN_OBS>   44166.2383     </MEAN_OBS>
 <STDV_OBS>   20268.7773     </STDV_OBS>
 <EXP>
 <ID>        2245 </ID>
 <NAME>REF</NAME>
 <NUM>         319 </NUM>
 <MEAN>   23230.2188     </MEAN>
 <STDV>  -3.74686968E-20 </STDV>
 <BIAS>   24131.7402     </BIAS>
 <RMSE>   1.46152731E-02 </RMSE>
 <CORR>  -3.74675594E-20 </CORR>
 </EXP>
 <EXP>
 <ID>        2245 </ID>
 <NAME>SAR_2</NAME>
 <NUM>         319 </NUM>
 <MEAN>   0.00000000     </MEAN>
 <STDV>   0.00000000     </STDV>
 <BIAS>   24147.9648     </BIAS>
 <RMSE>   2.63625011E-02 </RMSE>
 <CORR>   0.00000000     </CORR>
 </EXP>
 </STATION>
 <STATION>
 <MEAN_OBS>   33409.6953     </MEAN_OBS>
 <STDV_OBS>   20654.0098     </STDV_OBS>
 <EXP>
 <ID>        2254 </ID>
 <NAME>REF</NAME>
 <NUM>         330 </NUM>
 <MEAN>   22591.3008     </MEAN>
 <STDV>  -3.74676628E-20 </STDV>
 <BIAS>   23233.7539     </BIAS>
 <RMSE>  0.379772842     </RMSE>
 <CORR>  -3.74677662E-20 </CORR>
 </EXP>
 <EXP>
 <ID>        2254 </ID>
 <NAME>SAR_2</NAME>
 <NUM>         330 </NUM>
 <MEAN>   1.40129846E-45 </MEAN>
 <STDV>   0.00000000     </STDV>
 <BIAS>   22982.7168     </BIAS>
 <RMSE>  0.390487343     </RMSE>
 <CORR>   0.00000000     </CORR>
 </EXP>
 </STATION>
 <STATION>
 <MEAN_OBS>   46791.4688     </MEAN_OBS>
 <STDV_OBS>   20434.7461     </STDV_OBS>
 <EXP>
 <ID>        2260 </ID>
 <NAME>REF</NAME>
 <NUM>         327 </NUM>
 <MEAN>   24348.9102     </MEAN>
 <STDV>  -3.74675594E-20 </STDV>
 <BIAS>   20593.8164     </BIAS>
 <RMSE>  0.223315611     </RMSE>
 <CORR>   3.35176886E-11 </CORR>
 </EXP>
 <EXP>
 <ID>        2260 </ID>
 <NAME>SAR_2</NAME>
 <NUM>         327 </NUM>
 <MEAN>   0.00000000     </MEAN>
 <STDV>   0.00000000     </STDV>
 <BIAS>   20432.1641     </BIAS>
 <RMSE>  0.257404327     </RMSE>
 <CORR>   1.40129846E-45 </CORR>
 </EXP>
 </STATION>
 <STATION>
 <MEAN_OBS>   46526.2109     </MEAN_OBS>
 <STDV_OBS>   19410.7031     </STDV_OBS>
 <EXP>
 <ID>        2261 </ID>
 <NAME>REF</NAME>
 <NUM>         330 </NUM>
 <MEAN>   26369.5508     </MEAN>
 <STDV>  -3.74685934E-20 </STDV>
 <BIAS>   19340.2773     </BIAS>
 <RMSE>  0.193769559     </RMSE>
 <CORR>   3.35181327E-11 </CORR>
 </EXP>
 <EXP>
 <ID>        2261 </ID>
 <NAME>SAR_2</NAME>
 <NUM>         330 </NUM>
 <MEAN>   1.40129846E-45 </MEAN>
 <STDV>   0.00000000     </STDV>
 <BIAS>   19376.0332     </BIAS>
 <RMSE>  0.209804580     </RMSE>
 <CORR>   1.40129846E-45 </CORR>
 </EXP>
 </STATION>
 <STATION>
 <MEAN_OBS>   43893.0156     </MEAN_OBS>
 <STDV_OBS>   20773.2227     </STDV_OBS>
 <EXP>
 <ID>        2263 </ID>
 <NAME>REF</NAME>
 <NUM>         328 </NUM>
 <MEAN>   23128.7891     </MEAN>
 <STDV>   3.34758332E-11 </STDV>
 <BIAS>   21555.9414     </BIAS>
 <RMSE>  0.279045314     </RMSE>
 <CORR>  -3.74677662E-20 </CORR>
 </EXP>
 <EXP>
 <ID>        2263 </ID>
 <NAME>SAR_2</NAME>
 <NUM>         328 </NUM>
 <MEAN>   0.00000000     </MEAN>
 <STDV>   1.40129846E-45 </STDV>
 <BIAS>   21670.1289     </BIAS>
 <RMSE>  0.276828021     </RMSE>
 <CORR>   0.00000000     </CORR>
 </EXP>
 </STATION>
 <STATION>
 <MEAN_OBS>   45115.7852     </MEAN_OBS>
 <STDV_OBS>   20450.5684     </STDV_OBS>
 <EXP>
 <ID>        2265 </ID>
 <NAME>REF</NAME>
 <NUM>         330 </NUM>
 <MEAN>   24207.6582     </MEAN>
 <STDV>   3.35181327E-11 </STDV>
 <BIAS>   20960.5508     </BIAS>
 <RMSE>  0.235761046     </RMSE>
 <CORR>   3.35176886E-11 </CORR>
 </EXP>
 <EXP>
 <ID>        2265 </ID>
 <NAME>SAR_2</NAME>
 <NUM>         330 </NUM>
 <MEAN>   1.40129846E-45 </MEAN>
 <STDV>   1.40129846E-45 </STDV>
 <BIAS>   20739.3652     </BIAS>
 <RMSE>  0.264045358     </RMSE>
 <CORR>   1.40129846E-45 </CORR>
 </EXP>
 </STATION>
 <STATION>
 <MEAN_OBS>   29675.6035     </MEAN_OBS>
 <STDV_OBS>   19208.3066     </STDV_OBS>
 <EXP>
 <ID>        2219 </ID>
 <NAME>REF</NAME>
 <NUM>         323 </NUM>
 <MEAN>   23384.1797     </MEAN>
 <STDV>  -3.74677662E-20 </STDV>
 <BIAS>   24113.0586     </BIAS>
 <RMSE>   7.12226182E-02 </RMSE>
 <CORR>  -3.74684900E-20 </CORR>
 </EXP>
 <EXP>
 <ID>        2219 </ID>
 <NAME>SAR_2</NAME>
 <NUM>         323 </NUM>
 <MEAN>   0.00000000     </MEAN>
 <STDV>   0.00000000     </STDV>
 <BIAS>   23968.3809     </BIAS>
 <RMSE>   5.98942339E-02 </RMSE>
 <CORR>   0.00000000     </CORR>
 </EXP>
 </STATION>
 <STATION>
 <MEAN_OBS>   43865.4336     </MEAN_OBS>
 <STDV_OBS>   19817.1328     </STDV_OBS>
 <EXP>
 <ID>        2243 </ID>
 <NAME>REF</NAME>
 <NUM>         311 </NUM>
 <MEAN>   18688.7188     </MEAN>
 <STDV>  -3.74686968E-20 </STDV>
 <BIAS>   21509.7324     </BIAS>
 <RMSE>  0.158607602     </RMSE>
 <CORR>   3.35180217E-11 </CORR>
 </EXP>
 <EXP>
 <ID>        2243 </ID>
 <NAME>SAR_2</NAME>
 <NUM>         311 </NUM>
 <MEAN>   0.00000000     </MEAN>
 <STDV>   0.00000000     </STDV>
 <BIAS>   22105.4805     </BIAS>
 <RMSE>  0.124727726     </RMSE>
 <CORR>   1.40129846E-45 </CORR>
 </EXP>
 </STATION>
 <STATION>
 <MEAN_OBS>   11924.2422     </MEAN_OBS>
 <STDV_OBS>   9696.36426     </STDV_OBS>
 <EXP>
 <ID>        1062 </ID>
 <NAME>REF</NAME>
 <NUM>         330 </NUM>
 <MEAN>   45356.4336     </MEAN>
 <STDV>  -3.74676628E-20 </STDV>
 <BIAS>   9306.52734     </BIAS>
 <RMSE>  -1.29875250E-03 </RMSE>
 <CORR>   3.35176886E-11 </CORR>
 </EXP>
 <EXP>
 <ID>        1062 </ID>
 <NAME>SAR_2</NAME>
 <NUM>         330 </NUM>
 <MEAN>   0.00000000     </MEAN>
 <STDV>   0.00000000     </STDV>
 <BIAS>   9986.78125     </BIAS>
 <RMSE>   1.06635904E-02 </RMSE>
 <CORR>   1.40129846E-45 </CORR>
 </EXP>
 </STATION>
 <STATION>
 <MEAN_OBS>   19048.6895     </MEAN_OBS>
 <STDV_OBS>   20533.0371     </STDV_OBS>
 <EXP>
 <ID>        1001 </ID>
 <NAME>REF</NAME>
 <NUM>         267 </NUM>
 <MEAN>   26636.7656     </MEAN>
 <STDV>  -3.74676628E-20 </STDV>
 <BIAS>   15283.8145     </BIAS>
 <RMSE>  0.659174681     </RMSE>
 <CORR>  -3.74684900E-20 </CORR>
 </EXP>
 <EXP>
 <ID>        1001 </ID>
 <NAME>SAR_2</NAME>
 <NUM>         267 </NUM>
 <MEAN>   0.00000000     </MEAN>
 <STDV>   0.00000000     </STDV>
 <BIAS>   16408.4023     </BIAS>
 <RMSE>  0.604155123     </RMSE>
 <CORR>   0.00000000     </CORR>
 </EXP>
 </STATION>
 <STATION>
 <MEAN_OBS>   46491.1875     </MEAN_OBS>
 <STDV_OBS>   16922.1738     </STDV_OBS>
 <EXP>
 <ID>        1023 </ID>
 <NAME>REF</NAME>
 <NUM>         227 </NUM>
 <MEAN>   25177.3281     </MEAN>
 <STDV>  -3.74675594E-20 </STDV>
 <BIAS>   24965.9062     </BIAS>
 <RMSE>  0.130488098     </RMSE>
 <CORR>   3.35181327E-11 </CORR>
 </EXP>
 <EXP>
 <ID>        1023 </ID>
 <NAME>SAR_2</NAME>
 <NUM>         227 </NUM>
 <MEAN>   0.00000000     </MEAN>
 <STDV>   0.00000000     </STDV>
 <BIAS>   24709.4629     </BIAS>
 <RMSE>  0.167218611     </RMSE>
 <CORR>   1.40129846E-45 </CORR>
 </EXP>
 </STATION>
 <STATION>
 <MEAN_OBS>   32988.8242     </MEAN_OBS>
 <STDV_OBS>   16267.8408     </STDV_OBS>
 <EXP>
 <ID>        1025 </ID>
 <NAME>REF</NAME>
 <NUM>         136 </NUM>
 <MEAN>   27062.1582     </MEAN>
 <STDV>   3.35180217E-11 </STDV>
 <BIAS>   24518.0488     </BIAS>
 <RMSE>  0.197541311     </RMSE>
 <CORR>   3.35181327E-11 </CORR>
 </EXP>
 <EXP>
 <ID>        1025 </ID>
 <NAME>SAR_2</NAME>
 <NUM>         136 </NUM>
 <MEAN>   0.00000000     </MEAN>
 <STDV>   1.40129846E-45 </STDV>
 <BIAS>   25365.8105     </BIAS>
 <RMSE>  0.103117824     </RMSE>
 <CORR>   1.40129846E-45 </CORR>
 </EXP>
 </STATION>
 <STATION>
 <MEAN_OBS>   11737.7295     </MEAN_OBS>
 <STDV_OBS>   21360.7793     </STDV_OBS>
 <EXP>
 <ID>        1028 </ID>
 <NAME>REF</NAME>
 <NUM>         326 </NUM>
 <MEAN>   29365.6074     </MEAN>
 <STDV>  -3.74675594E-20 </STDV>
 <BIAS>   15775.0332     </BIAS>
 <RMSE>  0.753446102     </RMSE>
 <CORR>   3.35176886E-11 </CORR>
 </EXP>
 <EXP>
 <ID>        1028 </ID>
 <NAME>SAR_2</NAME>
 <NUM>         326 </NUM>
 <MEAN>   0.00000000     </MEAN>
 <STDV>   0.00000000     </STDV>
 <BIAS>   16697.3301     </BIAS>
 <RMSE>  0.695353866     </RMSE>
 <CORR>   1.40129846E-45 </CORR>
 </EXP>
 </STATION>
 <STATION>
 <MEAN_OBS>   38600.0000     </MEAN_OBS>
 <STDV_OBS>   16955.4062     </STDV_OBS>
 <EXP>
 <ID>        2862 </ID>
 <NAME>REF</NAME>
 <NUM>         330 </NUM>
 <MEAN>   30904.9629     </MEAN>
 <STDV>   3.34758332E-11 </STDV>
 <BIAS>   19719.3262     </BIAS>
 <RMSE>  0.335047126     </RMSE>
 <CORR>   3.35181327E-11 </CORR>
 </EXP>
 <EXP>
 <ID>        2862 </ID>
 <NAME>SAR_2</NAME>
 <NUM>         330 </NUM>
 <MEAN>   1.40129846E-45 </MEAN>
 <STDV>   1.40129846E-45 </STDV>
 <BIAS>   19828.6270     </BIAS>
 <RMSE>  0.328681737     </RMSE>
 <CORR>   1.40129846E-45 </CORR>
 </EXP>
 </STATION>
 <STATION>
 <MEAN_OBS>   57609.8477     </MEAN_OBS>
 <STDV_OBS>   18412.0273     </STDV_OBS>
 <EXP>
 <ID>        2807 </ID>
 <NAME>REF</NAME>
 <NUM>         330 </NUM>
 <MEAN>   25008.7969     </MEAN>
 <STDV>   3.35180217E-11 </STDV>
 <BIAS>   25705.3750     </BIAS>
 <RMSE>  0.240953729     </RMSE>
 <CORR>   3.35176886E-11 </CORR>
 </EXP>
 <EXP>
 <ID>        2807 </ID>
 <NAME>SAR_2</NAME>
 <NUM>         330 </NUM>
 <MEAN>   0.00000000     </MEAN>
 <STDV>   1.40129846E-45 </STDV>
 <BIAS>   27041.7559     </BIAS>
 <RMSE>  0.152691081     </RMSE>
 <CORR>   1.40129846E-45 </CORR>
 </EXP>
 </STATION>
 <STATION>
 <MEAN_OBS>   39486.6641     </MEAN_OBS>
 <STDV_OBS>   19245.2773     </STDV_OBS>
 <EXP>
 <ID>        2880 </ID>
 <NAME>REF</NAME>
 <NUM>         330 </NUM>
 <MEAN>   23753.4160     </MEAN>
 <STDV>  -3.74677662E-20 </STDV>
 <BIAS>   22634.3496     </BIAS>
 <RMSE>  0.212138385     </RMSE>
 <CORR>  -3.74684900E-20 </CORR>
 </EXP>
 <EXP>
 <ID>        2880 </ID>
 <NAME>SAR_2</NAME>
 <NUM>         330 </NUM>
 <MEAN>   0.00000000     </MEAN>
 <STDV>   0.00000000     </STDV>
 <BIAS>   22683.2500     </BIAS>
 <RMSE>  0.211075500     </RMSE>
 <CORR>   0.00000000     </CORR>
 </EXP>
 </STATION>
 <STATION>
 <MEAN_OBS>   30393.9375     </MEAN_OBS>
 <STDV_OBS>   19224.5703     </STDV_OBS>
 <EXP>
 <ID>        2844 </ID>
 <NAME>REF</NAME>
 <NUM>         330 </NUM>
 <MEAN>   16521.0801     </MEAN>
 <STDV>  -3.74686968E-20 </STDV>
 <BIAS>   21490.3496     </BIAS>
 <RMSE>  0.310285866     </RMSE>
 <CORR>   3.35181327E-11 </CORR>
 </EXP>
 <EXP>
 <ID>        2844 </ID>
 <NAME>SAR_2</NAME>
 <NUM>         330 </NUM>
 <MEAN>   0.00000000     </MEAN>
 <STDV>   0.00000000     </STDV>
 <BIAS>   21405.5547     </BIAS>
 <RMSE>  0.334363639     </RMSE>
 <CORR>   1.40129846E-45 </CORR>
 </EXP>
 </STATION>
 <STATION>
 <MEAN_OBS>   11629.8174     </MEAN_OBS>
 <STDV_OBS>   18600.0156     </STDV_OBS>
 <EXP>
 <ID>        2845 </ID>
 <NAME>REF</NAME>
 <NUM>         330 </NUM>
 <MEAN>   14683.1934     </MEAN>
 <STDV>  -3.74676628E-20 </STDV>
 <BIAS>   17391.3574     </BIAS>
 <RMSE>  0.334399581     </RMSE>
 <CORR>   3.35176886E-11 </CORR>
 </EXP>
 <EXP>
 <ID>        2845 </ID>
 <NAME>SAR_2</NAME>
 <NUM>         330 </NUM>
 <MEAN>   0.00000000     </MEAN>
 <STDV>   0.00000000     </STDV>
 <BIAS>   17556.0352     </BIAS>
 <RMSE>  0.343741566     </RMSE>
 <CORR>   1.40129846E-45 </CORR>
 </EXP>
 </STATION>
 <STATION>
 <MEAN_OBS>   33350.7578     </MEAN_OBS>
 <STDV_OBS>   19924.4199     </STDV_OBS>
 <EXP>
 <ID>        2836 </ID>
 <NAME>REF</NAME>
 <NUM>         330 </NUM>
 <MEAN>   18733.9863     </MEAN>
 <STDV>  -3.74675594E-20 </STDV>
 <BIAS>   20798.2578     </BIAS>
 <RMSE>  0.431382060     </RMSE>
 <CORR>  -3.74684900E-20 </CORR>
 </EXP>
 <EXP>
 <ID>        2836 </ID>
 <NAME>SAR_2</NAME>
 <NUM>         330 </NUM>
 <MEAN>   0.00000000     </MEAN>
 <STDV>   0.00000000     </STDV>
 <BIAS>   21259.7891     </BIAS>
 <RMSE>  0.413780242     </RMSE>
 <CORR>   0.00000000     </CORR>
 </EXP>
 </STATION>
 <STATION>
 <MEAN_OBS>   26098.9688     </MEAN_OBS>
 <STDV_OBS>   19116.5762     </STDV_OBS>
 <EXP>
 <ID>        2814 </ID>
 <NAME>REF</NAME>
 <NUM>         330 </NUM>
 <MEAN>   15466.0225     </MEAN>
 <STDV>  -3.74685934E-20 </STDV>
 <BIAS>   21750.2188     </BIAS>
 <RMSE>  0.399669588     </RMSE>
 <CORR>   3.35181327E-11 </CORR>
 </EXP>
 <EXP>
 <ID>        2814 </ID>
 <NAME>SAR_2</NAME>
 <NUM>         330 </NUM>
 <MEAN>   1.40129846E-45 </MEAN>
 <STDV>   0.00000000     </STDV>
 <BIAS>   22412.4395     </BIAS>
 <RMSE>  0.377576947     </RMSE>
 <CORR>   1.40129846E-45 </CORR>
 </EXP>
 </STATION>
 <STATION>
 <MEAN_OBS>   15783.4443     </MEAN_OBS>
 <STDV_OBS>   20027.9395     </STDV_OBS>
 <EXP>
 <ID>        2849 </ID>
 <NAME>REF</NAME>
 <NUM>         328 </NUM>
 <MEAN>   20640.3789     </MEAN>
 <STDV>   3.34758332E-11 </STDV>
 <BIAS>   18307.0020     </BIAS>
 <RMSE>  0.379371703     </RMSE>
 <CORR>   3.35176886E-11 </CORR>
 </EXP>
 <EXP>
 <ID>        2849 </ID>
 <NAME>SAR_2</NAME>
 <NUM>         328 </NUM>
 <MEAN>   1.40129846E-45 </MEAN>
 <STDV>   1.40129846E-45 </STDV>
 <BIAS>   18484.2988     </BIAS>
 <RMSE>  0.386669695     </RMSE>
 <CORR>   1.40129846E-45 </CORR>
 </EXP>
 </STATION>
 <STATION>
 <MEAN_OBS>   16005.0303     </MEAN_OBS>
 <STDV_OBS>   18218.7363     </STDV_OBS>
 <EXP>
 <ID>        2801 </ID>
 <NAME>REF</NAME>
 <NUM>         330 </NUM>
 <MEAN>   14771.2070     </MEAN>
 <STDV>   3.35180217E-11 </STDV>
 <BIAS>   18122.3496     </BIAS>
 <RMSE>  0.245643392     </RMSE>
 <CORR>  -3.74684900E-20 </CORR>
 </EXP>
 <EXP>
 <ID>        2801 </ID>
 <NAME>SAR_2</NAME>
 <NUM>         330 </NUM>
 <MEAN>   0.00000000     </MEAN>
 <STDV>   1.40129846E-45 </STDV>
 <BIAS>   17869.6016     </BIAS>
 <RMSE>  0.230767265     </RMSE>
 <CORR>   0.00000000     </CORR>
 </EXP>
 </STATION>
 <STATION>
 <MEAN_OBS>   38644.3633     </MEAN_OBS>
 <STDV_OBS>   19185.9258     </STDV_OBS>
 <EXP>
 <ID>        2805 </ID>
 <NAME>REF</NAME>
 <NUM>         330 </NUM>
 <MEAN>   20732.1895     </MEAN>
 <STDV>  -3.74677662E-20 </STDV>
 <BIAS>   22677.6152     </BIAS>
 <RMSE>  0.241151571     </RMSE>
 <CORR>   3.35181327E-11 </CORR>
 </EXP>
 <EXP>
 <ID>        2805 </ID>
 <NAME>SAR_2</NAME>
 <NUM>         330 </NUM>
 <MEAN>   0.00000000     </MEAN>
 <STDV>   0.00000000     </STDV>
 <BIAS>   21744.6699     </BIAS>
 <RMSE>  0.275777787     </RMSE>
 <CORR>   1.40129846E-45 </CORR>
 </EXP>
 </STATION>
 <STATION>
 <MEAN_OBS>   40795.3320     </MEAN_OBS>
 <STDV_OBS>   18562.2441     </STDV_OBS>
 <EXP>
 <ID>        2835 </ID>
 <NAME>REF</NAME>
 <NUM>         330 </NUM>
 <MEAN>   24302.7969     </MEAN>
 <STDV>  -3.74686968E-20 </STDV>
 <BIAS>   20420.2227     </BIAS>
 <RMSE>  0.277809083     </RMSE>
 <CORR>   3.35176886E-11 </CORR>
 </EXP>
 <EXP>
 <ID>        2835 </ID>
 <NAME>SAR_2</NAME>
 <NUM>         330 </NUM>
 <MEAN>   0.00000000     </MEAN>
 <STDV>   0.00000000     </STDV>
 <BIAS>   19895.8672     </BIAS>
 <RMSE>  0.303713471     </RMSE>
 <CORR>   1.40129846E-45 </CORR>
 </EXP>
 </STATION>
 <STATION>
 <MEAN_OBS>   58833.3320     </MEAN_OBS>
 <STDV_OBS>   8247.74023     </STDV_OBS>
 <EXP>
 <ID>        1008 </ID>
 <NAME>REF</NAME>
 <NUM>         330 </NUM>
 <MEAN>   44851.3320     </MEAN>
 <STDV>  -3.74676628E-20 </STDV>
 <BIAS>   16378.5312     </BIAS>
 <RMSE>  0.420324773     </RMSE>
 <CORR>  -3.74684900E-20 </CORR>
 </EXP>
 <EXP>
 <ID>        1008 </ID>
 <NAME>SAR_2</NAME>
 <NUM>         330 </NUM>
 <MEAN>   0.00000000     </MEAN>
 <STDV>   0.00000000     </STDV>
 <BIAS>   17530.0664     </BIAS>
 <RMSE>  0.287764966     </RMSE>
 <CORR>   0.00000000     </CORR>
 </EXP>
 </STATION>
 <STATION>
 <MEAN_OBS>   42013.9297     </MEAN_OBS>
 <STDV_OBS>   16482.0078     </STDV_OBS>
 <EXP>
 <ID>        1026 </ID>
 <NAME>REF</NAME>
 <NUM>         323 </NUM>
 <MEAN>   26131.8262     </MEAN>
 <STDV>  -3.74675594E-20 </STDV>
 <BIAS>   25978.1426     </BIAS>
 <RMSE>  0.220202640     </RMSE>
 <CORR>   3.35181327E-11 </CORR>
 </EXP>
 <EXP>
 <ID>        1026 </ID>
 <NAME>SAR_2</NAME>
 <NUM>         323 </NUM>
 <MEAN>   0.00000000     </MEAN>
 <STDV>   0.00000000     </STDV>
 <BIAS>   26268.5918     </BIAS>
 <RMSE>  0.194974929     </RMSE>
 <CORR>   1.40129846E-45 </CORR>
 </EXP>
 </STATION>
 <STATION>
 <MEAN_OBS>   26119.8164     </MEAN_OBS>
 <STDV_OBS>   19495.5684     </STDV_OBS>
 <EXP>
 <ID>        2847 </ID>
 <NAME>REF</NAME>
 <NUM>         330 </NUM>
 <MEAN>   21677.1758     </MEAN>
 <STDV>  -3.74675594E-20 </STDV>
 <BIAS>   21735.8770     </BIAS>
 <RMSE>  0.308537811     </RMSE>
 <CORR>   3.35176886E-11 </CORR>
 </EXP>
 <EXP>
 <ID>        2847 </ID>
 <NAME>SAR_2</NAME>
 <NUM>         330 </NUM>
 <MEAN>   0.00000000     </MEAN>
 <STDV>   0.00000000     </STDV>
 <BIAS>   22621.6758     </BIAS>
 <RMSE>  0.260828346     </RMSE>
 <CORR>   1.40129846E-45 </CORR>
 </EXP>
 </STATION>
 <STATION>
 <MEAN_OBS>   16972.1855     </MEAN_OBS>
 <STDV_OBS>   18520.4785     </STDV_OBS>
 <EXP>
 <ID>        2821 </ID>
 <NAME>REF</NAME>
 <NUM>         279 </NUM>
 <MEAN>   13594.9355     </MEAN>
 <STDV>  -3.74686968E-20 </STDV>
 <BIAS>   18632.6426     </BIAS>
 <RMSE>  0.594881892     </RMSE>
 <CORR>   3.35181327E-11 </CORR>
 </EXP>
 <EXP>
 <ID>        2821 </ID>
 <NAME>SAR_2</NAME>
 <NUM>         279 </NUM>
 <MEAN>   0.00000000     </MEAN>
 <STDV>   0.00000000     </STDV>
 <BIAS>   18678.1738     </BIAS>
 <RMSE>  0.582753718     </RMSE>
 <CORR>   1.40129846E-45 </CORR>
 </EXP>
 </STATION>
 <STATION>
 <MEAN_OBS>   16145.2422     </MEAN_OBS>
 <STDV_OBS>   19075.5684     </STDV_OBS>
 <EXP>
 <ID>        2717 </ID>
 <NAME>REF</NAME>
 <NUM>         330 </NUM>
 <MEAN>   16324.5996     </MEAN>
 <STDV>  -3.74677662E-20 </STDV>
 <BIAS>   17735.2207     </BIAS>
 <RMSE>  0.342376143     </RMSE>
 <CORR>  -3.74675594E-20 </CORR>
 </EXP>
 <EXP>
 <ID>        2717 </ID>
 <NAME>SAR_2</NAME>
 <NUM>         330 </NUM>
 <MEAN>   1.40129846E-45 </MEAN>
 <STDV>   0.00000000     </STDV>
 <BIAS>   17731.9219     </BIAS>
 <RMSE>  0.366122663     </RMSE>
 <CORR>   0.00000000     </CORR>
 </EXP>
 </STATION>
 <STATION>
 <MEAN_OBS>   28279.5449     </MEAN_OBS>
 <STDV_OBS>   18623.1035     </STDV_OBS>
 <EXP>
 <ID>        2726 </ID>
 <NAME>REF</NAME>
 <NUM>         330 </NUM>
 <MEAN>   16084.2051     </MEAN>
 <STDV>  -3.74686968E-20 </STDV>
 <BIAS>   21491.9434     </BIAS>
 <RMSE>  0.423343509     </RMSE>
 <CORR>  -3.74684900E-20 </CORR>
 </EXP>
 <EXP>
 <ID>        2726 </ID>
 <NAME>SAR_2</NAME>
 <NUM>         330 </NUM>
 <MEAN>   0.00000000     </MEAN>
 <STDV>   0.00000000     </STDV>
 <BIAS>   21343.0430     </BIAS>
 <RMSE>  0.409743041     </RMSE>
 <CORR>   0.00000000     </CORR>
 </EXP>
 </STATION>
 <STATION>
 <MEAN_OBS>   17456.6055     </MEAN_OBS>
 <STDV_OBS>   19239.4980     </STDV_OBS>
 <EXP>
 <ID>        2857 </ID>
 <NAME>REF</NAME>
 <NUM>         330 </NUM>
 <MEAN>   20269.6641     </MEAN>
 <STDV>  -3.74676628E-20 </STDV>
 <BIAS>   18707.1973     </BIAS>
 <RMSE>  0.289380014     </RMSE>
 <CORR>  -3.74675594E-20 </CORR>
 </EXP>
 <EXP>
 <ID>        2857 </ID>
 <NAME>SAR_2</NAME>
 <NUM>         330 </NUM>
 <MEAN>   0.00000000     </MEAN>
 <STDV>   0.00000000     </STDV>
 <BIAS>   18792.0703     </BIAS>
 <RMSE>  0.224571258     </RMSE>
 <CORR>   0.00000000     </CORR>
 </EXP>
 </STATION>
 <STATION>
 <MEAN_OBS>   18107.9395     </MEAN_OBS>
 <STDV_OBS>   19206.6367     </STDV_OBS>
 <EXP>
 <ID>        2702 </ID>
 <NAME>REF</NAME>
 <NUM>         330 </NUM>
 <MEAN>   21748.7578     </MEAN>
 <STDV>  -3.74677662E-20 </STDV>
 <BIAS>   18987.0645     </BIAS>
 <RMSE>  0.250124723     </RMSE>
 <CORR>  -3.74676628E-20 </CORR>
 </EXP>
 <EXP>
 <ID>        2702 </ID>
 <NAME>SAR_2</NAME>
 <NUM>         330 </NUM>
 <MEAN>   1.40129846E-45 </MEAN>
 <STDV>   0.00000000     </STDV>
 <BIAS>   18658.3340     </BIAS>
 <RMSE>  0.233009681     </RMSE>
 <CORR>   0.00000000     </CORR>
 </EXP>
 </STATION>
 <STATION>
 <MEAN_OBS>   40563.6953     </MEAN_OBS>
 <STDV_OBS>   19649.3203     </STDV_OBS>
 <EXP>
 <ID>        2864 </ID>
 <NAME>REF</NAME>
 <NUM>         330 </NUM>
 <MEAN>   22285.1582     </MEAN>
 <STDV>  -3.74685934E-20 </STDV>
 <BIAS>   26074.5508     </BIAS>
 <RMSE>  0.229232520     </RMSE>
 <CORR>   3.35181327E-11 </CORR>
 </EXP>
 <EXP>
 <ID>        2864 </ID>
 <NAME>SAR_2</NAME>
 <NUM>         330 </NUM>
 <MEAN>   0.00000000     </MEAN>
 <STDV>   0.00000000     </STDV>
 <BIAS>   25766.7988     </BIAS>
 <RMSE>  0.244712055     </RMSE>
 <CORR>   1.40129846E-45 </CORR>
 </EXP>
 </STATION>
 <STATION>
 <MEAN_OBS>   23771.1504     </MEAN_OBS>
 <STDV_OBS>   19405.2812     </STDV_OBS>
 <EXP>
 <ID>        2881 </ID>
 <NAME>REF</NAME>
 <NUM>         330 </NUM>
 <MEAN>   15013.0801     </MEAN>
 <STDV>  -3.74686968E-20 </STDV>
 <BIAS>   22186.5566     </BIAS>
 <RMSE>  0.354317456     </RMSE>
 <CORR>   3.35176886E-11 </CORR>
 </EXP>
 <EXP>
 <ID>        2881 </ID>
 <NAME>SAR_2</NAME>
 <NUM>         330 </NUM>
 <MEAN>   0.00000000     </MEAN>
 <STDV>   0.00000000     </STDV>
 <BIAS>   23116.3340     </BIAS>
 <RMSE>  0.314320236     </RMSE>
 <CORR>   1.40129846E-45 </CORR>
 </EXP>
 </STATION>
 <STATION>
 <MEAN_OBS>   47335.6953     </MEAN_OBS>
 <STDV_OBS>   20041.4727     </STDV_OBS>
 <EXP>
 <ID>        2720 </ID>
 <NAME>REF</NAME>
 <NUM>         330 </NUM>
 <MEAN>   19338.0586     </MEAN>
 <STDV>  -3.74684900E-20 </STDV>
 <BIAS>   30465.6875     </BIAS>
 <RMSE>  0.337854564     </RMSE>
 <CORR>  -3.74676628E-20 </CORR>
 </EXP>
 <EXP>
 <ID>        2720 </ID>
 <NAME>SAR_2</NAME>
 <NUM>         330 </NUM>
 <MEAN>   0.00000000     </MEAN>
 <STDV>   0.00000000     </STDV>
 <BIAS>   31583.8535     </BIAS>
 <RMSE>  0.283622593     </RMSE>
 <CORR>   0.00000000     </CORR>
 </EXP>
 </STATION>
 <STATION>
 <MEAN_OBS>   29484.1504     </MEAN_OBS>
 <STDV_OBS>   20226.0098     </STDV_OBS>
 <EXP>
 <ID>        2816 </ID>
 <NAME>REF</NAME>
 <NUM>         330 </NUM>
 <MEAN>   18291.5195     </MEAN>
 <STDV>  -3.74676628E-20 </STDV>
 <BIAS>   21843.1934     </BIAS>
 <RMSE>  0.417875230     </RMSE>
 <CORR>   3.35176886E-11 </CORR>
 </EXP>
 <EXP>
 <ID>        2816 </ID>
 <NAME>SAR_2</NAME>
 <NUM>         330 </NUM>
 <MEAN>   1.40129846E-45 </MEAN>
 <STDV>   0.00000000     </STDV>
 <BIAS>   22001.6621     </BIAS>
 <RMSE>  0.403031498     </RMSE>
 <CORR>   1.40129846E-45 </CORR>
 </EXP>
 </STATION>
 <STATION>
 <MEAN_OBS>   16083.9385     </MEAN_OBS>
 <STDV_OBS>   21757.1172     </STDV_OBS>
 <EXP>
 <ID>        1003 </ID>
 <NAME>REF</NAME>
 <NUM>         330 </NUM>
 <MEAN>   27879.1289     </MEAN>
 <STDV>  -3.74685934E-20 </STDV>
 <BIAS>   16678.5527     </BIAS>
 <RMSE>  0.652237892     </RMSE>
 <CORR>   3.35180217E-11 </CORR>
 </EXP>
 <EXP>
 <ID>        1003 </ID>
 <NAME>SAR_2</NAME>
 <NUM>         330 </NUM>
 <MEAN>   0.00000000     </MEAN>
 <STDV>   0.00000000     </STDV>
 <BIAS>   15967.8828     </BIAS>
 <RMSE>  0.688483536     </RMSE>
 <CORR>   1.40129846E-45 </CORR>
 </EXP>
 </STATION>
 <STATION>
 <MEAN_OBS>   44336.7734     </MEAN_OBS>
 <STDV_OBS>   8750.67090     </STDV_OBS>
 <EXP>
 <ID>        1007 </ID>
 <NAME>REF</NAME>
 <NUM>         155 </NUM>
 <MEAN>   47909.5000     </MEAN>
 <STDV>  -3.74686968E-20 </STDV>
 <BIAS>   24871.3125     </BIAS>
 <RMSE>  0.139149696     </RMSE>
 <CORR>   3.35181327E-11 </CORR>
 </EXP>
 <EXP>
 <ID>        1007 </ID>
 <NAME>SAR_2</NAME>
 <NUM>         155 </NUM>
 <MEAN>   0.00000000     </MEAN>
 <STDV>   0.00000000     </STDV>
 <BIAS>   24898.2773     </BIAS>
 <RMSE>  0.127907261     </RMSE>
 <CORR>   1.40129846E-45 </CORR>
 </EXP>
 </STATION>
 <STATION>
 <MEAN_OBS>   48692.8828     </MEAN_OBS>
 <STDV_OBS>   19245.1055     </STDV_OBS>
 <EXP>
 <ID>        1047 </ID>
 <NAME>REF</NAME>
 <NUM>         267 </NUM>
 <MEAN>   18780.9297     </MEAN>
 <STDV>  -3.74684900E-20 </STDV>
 <BIAS>   23219.4238     </BIAS>
 <RMSE>  0.365393311     </RMSE>
 <CORR>   3.35176886E-11 </CORR>
 </EXP>
 <EXP>
 <ID>        1047 </ID>
 <NAME>SAR_2</NAME>
 <NUM>         267 </NUM>
 <MEAN>   0.00000000     </MEAN>
 <STDV>   0.00000000     </STDV>
 <BIAS>   22964.7930     </BIAS>
 <RMSE>  0.368177950     </RMSE>
 <CORR>   1.40129846E-45 </CORR>
 </EXP>
 </STATION>
</STAT>
